{
  "title": "香虎",
  "list_title": "香虎",
  "article_id": "125",
  "source_url": "https://www.iq3344.com/peijian/125/",
  "category_slug": "peijian",
  "category_name": "渔具配件",
  "category_order": "01",
  "position": 13,
  "date": "2024-01-20",
  "views": "75",
  "excerpt": "香虎诱鱼剂 香虎是钓鱼者常用的香味添加剂，具有浓郁的焦甜果香，对鲤鱼、鲫鱼、草鱼等多种鱼类都有极好的诱食效果。 香虎主要成分为乙基麦芽酚，也可选用乙基麦芽酚作为替代品。最佳...",
  "description": "香虎诱鱼剂 香虎是钓鱼者常用的香味添加剂，具有浓郁的焦甜果香，对鲤鱼、鲫鱼、草鱼等多种鱼类都有极好的诱食效果。 香虎主要成分为乙基麦芽酚，也可选用乙基麦芽酚作为替代品。最佳",
  "keywords": "香虎,诱鱼剂,香虎,诱鱼剂,是,钓鱼者,常用的,",
  "image_urls": [
    "https://www.iq3344.com/uploads/allimg/240120/1-240120005P90-L-lp.jpg",
    "https://www.iq3344.com/uploads/allimg/240120/1-240120005P90-L.jpg"
  ],
  "local_images": [
    "by_category/01_渔具配件/125_香虎/images/01_1-240120005P90-L-lp.jpg",
    "by_category/01_渔具配件/125_香虎/images/02_1-240120005P90-L.jpg"
  ],
  "local_dir": "by_category/01_渔具配件/125_香虎",
  "raw_line_count": 17,
  "text_sha256": "a7fa01ad2d23e12c4844e038ec135dfc3ee3f6fe8c06ccf1b2625cdf40310d4b"
}