{
  "name": "日本牛目鲷",
  "slug": "ri-ben-niu-mu-diao",
  "source_url": "https://fishweather.cn/fish/ri-ben-niu-mu-diao",
  "list_page": 33,
  "list_position": 772,
  "scientific_name": "Cookeolus japonicus",
  "aliases": "长棘松球鱼",
  "headline": "日本牛目鲷怎么钓？习性·钓法·饵料与真实钓获",
  "summary": "日本大眼鲷体型中等，呈卵圆形，侧扁。眼睛非常大且突出，占据头部很大比例，这也是其名称的由来。体色通常为鲜艳的红色或橙红色，有时带有银色光泽。身体覆盖着粗糙的栉鳞，背鳍和臀鳍具有强硬的棘刺，尾鳍呈叉形。口裂大，端位，颌骨具细齿。整体外观色彩鲜艳，形态独特，易于辨认。",
  "date_published": "2026-07-05",
  "date_modified": "2026-07-05",
  "fields": {
    "纲": "辐鳍鱼纲",
    "目": "鲈形目",
    "科": "大眼鲷科",
    "水层": "底层,近底层",
    "食性": "肉食性，主要以小型甲壳类动物（如虾、蟹）、小型鱼类、多毛类worms和其他底栖无脊椎动物为食。夜间活动觅食。",
    "栖息环境": "主要栖息于热带和亚热带海洋的珊瑚礁、岩礁区域以及近海大陆架。偏好清澈、水质良好的海域，常躲藏在岩石缝隙、洞穴或珊瑚丛中。",
    "体长": "30",
    "体重": "0.5",
    "寿命": "寿命较长，在自然海域中可能存活10年以上。具体寿命数据尚不明确，但一般热带珊瑚礁鱼类寿命相对较长。",
    "适温": "22-28"
  },
  "bait_options": [
    "南极虾",
    "虾肉",
    "鱿鱼块",
    "鱼肉块",
    "海蚯蚓",
    "沙蚕",
    "小螃蟹",
    "贝肉",
    "拟饵软虫",
    "小鱼型拟饵"
  ],
  "float_signals": [
    "黑漂",
    "：",
    "浮漂直接快速没入水中，消失不见，是明显的鱼吞饵信号。",
    "点动漂",
    "：",
    "浮漂出现轻微的点动或颤动，可能是鱼试探性触碰饵料。",
    "顿口",
    "：",
    "浮漂快速下沉半目或一目，然后停顿，通常是鱼咬钩的信号。",
    "慢拖漂",
    "：",
    "浮漂缓慢地向侧面或下方移动，可能是鱼拖动饵料。",
    "加速下沉",
    "：",
    "浮漂原本缓慢下沉，突然加速下沉，可能是鱼就饵。"
  ],
  "practical_tips": [
    "选择合适的钓点:日本大眼鲷喜欢栖息在礁石缝隙和洞穴中，钓点应选择这些区域附近。",
    "使用诱饵:提前打窝诱鱼，可以使用虾砖、南极虾等，提高上鱼率。",
    "耐心等待:大眼鲷属于慢口鱼，需要耐心等待鱼咬钩。",
    "注意防挂底:礁石区容易挂底，钓组要适当离底或使用防挂底钓组。",
    "夜钓效果好:日本大眼鲷夜间活动觅食，夜钓是更好的选择，可以使用夜光漂或电子漂。"
  ],
  "recommended_spots": "珊瑚礁区、岩礁区、沉船区、近海矶石、海岛周围",
  "distribution": [],
  "similar_fish": [
    "大眼鲷",
    "金鳞鱼",
    "soldierfish",
    "sabersquirrelfish",
    "斑马鱼"
  ],
  "images": {
    "fish": [
      "https://fishweather.cn/asset-images/fish/ri-ben-niu-mu-diao.webp"
    ],
    "catch": []
  },
  "profile_text_sha256": "d0b81bf64262ae645744a97a13fa827ac9ba139262ddbb714ddba283ec3475b3",
  "raw_line_count": 73,
  "local_dir": "by_family/大眼鲷科/ri-ben-niu-mu-diao_日本牛目鲷",
  "local_images": {
    "fish": [
      "by_family/大眼鲷科/ri-ben-niu-mu-diao_日本牛目鲷/images/main.webp"
    ],
    "catch": []
  }
}