{
  "name": "隆背笛鲷",
  "slug": "long-bei-di-diao",
  "source_url": "https://fishweather.cn/fish/long-bei-di-diao",
  "list_page": 19,
  "list_position": 456,
  "scientific_name": "Lutjanus gibbus",
  "aliases": "红槽、红鱼曹、凹槽、弓背笛鲷、石鲈、加力、赤笔仔",
  "headline": "隆背笛鲷怎么钓？习性·钓法·饵料与真实钓获",
  "summary": "体粗壮，略呈纺锤形，背部明显隆起，形成弓状背profile。体色鲜艳，成鱼通常为红色或橙红色，幼鱼体色偏浅，可能呈粉红色或黄色。嘴大，端位，上下颌牙齿尖锐，犬齿发达。眼眶下骨宽阔。",
  "date_published": "2026-07-05",
  "date_modified": "2026-07-05",
  "fields": {
    "纲": "辐鳍鱼纲",
    "目": "鲈形目",
    "科": "笛鲷科",
    "水层": "中下层",
    "食性": "肉食性，主要捕食小型鱼类、甲壳类（如虾、蟹）和头足类（如鱿鱼、章鱼）。",
    "栖息环境": "主要栖息于热带和亚热带珊瑚礁区及其附近海域，也可见于岩礁、红树林和潟湖等环境。",
    "体长": "50",
    "体重": "4",
    "寿命": "寿命较长，根据笛鲷属鱼类的一般特性推测，驼背笛鲷的寿命可能达到20年以上。",
    "适温": "22-28"
  },
  "bait_options": [
    "小鱼(如沙丁鱼",
    "秋刀鱼)",
    "虾(鲜虾",
    "南极虾)",
    "鱿鱼(鲜鱿鱼",
    "冰冻鱿鱼)",
    "拟饵(软饵:卷尾蛆",
    "T尾",
    "鱼形软饵)",
    "拟饵(硬饵:米诺",
    "铅笔",
    "波扒)",
    "海蜈蚣",
    "沙蚕",
    "鱼肉块(金枪鱼肉",
    "鲷鱼肉)",
    "贝肉(贻贝肉",
    "蛤蜊肉)",
    "螃蟹肉",
    "实战技巧",
    "找准鱼层:根据水深、潮汐、天气等因素判断鱼的活动水层，选择合适的钓法和钓组。",
    "选择合适饵料:根据季节、水域和目标鱼的食性选择合适的饵料或拟饵。",
    "注意潮汐变化:涨潮时鱼类通常更活跃，退潮时则可能退回深水区。",
    "慢速搜索:在不确定鱼情时，可采用慢速搜索的方式，扩大搜索范围。",
    "逗钓结合:在定点钓法中，可通过轻微抖动竿梢或提拉饵料，增加诱鱼效果。",
    "真实钓获",
    "来自钓鱼佬 App 用户的",
    "隆背笛鲷",
    "实战记录",
    "2026-01",
    "·",
    "北京市",
    "2.1",
    "kg",
    "22",
    "cm",
    "天气：",
    "水温7.9°C · 气压1024.8hPa · 溶氧11.2mg/L",
    "👍",
    "31",
    "钓友***",
    "相似鱼种",
    "赤点石斑鱼",
    "蓝鳍鲷",
    "真鲷",
    "黄鲷",
    "其他笛鲷"
  ],
  "float_signals": [],
  "practical_tips": [
    "找准鱼层:根据水深、潮汐、天气等因素判断鱼的活动水层，选择合适的钓法和钓组。",
    "选择合适饵料:根据季节、水域和目标鱼的食性选择合适的饵料或拟饵。",
    "注意潮汐变化:涨潮时鱼类通常更活跃，退潮时则可能退回深水区。",
    "慢速搜索:在不确定鱼情时，可采用慢速搜索的方式，扩大搜索范围。",
    "逗钓结合:在定点钓法中，可通过轻微抖动竿梢或提拉饵料，增加诱鱼效果。",
    "真实钓获",
    "来自钓鱼佬 App 用户的",
    "隆背笛鲷",
    "实战记录",
    "2026-01",
    "·",
    "北京市",
    "2.1",
    "kg",
    "22",
    "cm",
    "天气：",
    "水温7.9°C · 气压1024.8hPa · 溶氧11.2mg/L",
    "👍",
    "31",
    "钓友***",
    "相似鱼种",
    "赤点石斑鱼",
    "蓝鳍鲷",
    "真鲷",
    "黄鲷",
    "其他笛鲷"
  ],
  "recommended_spots": null,
  "distribution": [],
  "similar_fish": [
    "赤点石斑鱼",
    "蓝鳍鲷",
    "真鲷",
    "黄鲷",
    "其他笛鲷"
  ],
  "images": {
    "fish": [
      "https://fishweather.cn/asset-images/fish/long-bei-di-diao.webp"
    ],
    "catch": [
      "https://fishweather.cn/asset-images/catch/long-bei-di-diao-0-12fbbf20.webp"
    ]
  },
  "profile_text_sha256": "7e0f8e923dc4aeb8402d89d86beb6c964726addcd18cbda8a2c0254a7552267b",
  "raw_line_count": 80,
  "local_dir": "by_family/笛鲷科/long-bei-di-diao_隆背笛鲷",
  "local_images": {
    "fish": [
      "by_family/笛鲷科/long-bei-di-diao_隆背笛鲷/images/main.webp"
    ],
    "catch": []
  }
}