{
  "title": "子线尺",
  "list_title": "子线尺",
  "article_id": "122",
  "source_url": "https://www.iq3344.com/peijian/122/",
  "category_slug": "peijian",
  "category_name": "渔具配件",
  "category_order": "01",
  "position": 15,
  "date": "2024-01-20",
  "views": "153",
  "excerpt": "子线尺的作用 子线尺的主要功能是帮助钓鱼者精确绑制出长度、钩间距完全一致的子线，这样一来，在垂钓过程中需要更换子线时，就无需重新调整浮漂的位置了。 子线尺的使用方法 子线尺...",
  "description": "子线尺的作用 子线尺的主要功能是帮助钓鱼者精确绑制出长度、钩间距完全一致的子线，这样一来，在垂钓过程中需要更换子线时，就无需重新调整浮漂的位置了。 子线尺的使用方法 子线尺",
  "keywords": "子线尺",
  "image_urls": [
    "https://www.iq3344.com/uploads/allimg/240120/1-240120002030P8-lp.jpg",
    "https://www.iq3344.com/uploads/allimg/240120/1-240120002030P8.jpg"
  ],
  "local_images": [
    "by_category/01_渔具配件/122_子线尺/images/01_1-240120002030P8-lp.jpg",
    "by_category/01_渔具配件/122_子线尺/images/02_1-240120002030P8.jpg"
  ],
  "local_dir": "by_category/01_渔具配件/122_子线尺",
  "raw_line_count": 12,
  "text_sha256": "7542c4238cd5f8fd99cff30f2ead90dab639b6976462d13148784b704263417f"
}