{
  "name": "伸口鱼",
  "slug": "shen-kou-yu",
  "source_url": "https://fishweather.cn/fish/shen-kou-yu",
  "list_page": 22,
  "list_position": 505,
  "scientific_name": "Epibulus insidiator",
  "aliases": "无",
  "headline": "伸口鱼怎么钓？习性·钓法·饵料与真实钓获",
  "summary": "斜颌猪齿鱼体型中等，侧扁且延长。最显著的特征是其独特的口部结构，口部可以显著向前伸出，形成管状，用于捕食猎物。体色多变，幼鱼和成鱼颜色差异较大。幼鱼通常为黄色或橙色，随着成长颜色逐渐变为棕色、绿色或灰色，有时带有红色或橙色的斑点或条纹。眼睛上方突出，头部轮廓略呈三角形。",
  "date_published": "2026-07-05",
  "date_modified": "2026-07-05",
  "fields": {
    "纲": "辐鳍鱼纲",
    "目": "鲈形目",
    "科": "隆头鱼科",
    "水层": "中层,底层",
    "食性": "肉食性，主要以小型底栖无脊椎动物和小型鱼类为食。其伸缩自如的口部使其能够有效地捕捉到礁石缝隙或沙地中的猎物，如小型甲壳类、蠕虫、软体动物和幼鱼。",
    "栖息环境": "主要栖息于珊瑚礁区域，也可见于岩礁和海草床附近。幼鱼常在珊瑚丛或海葵中寻求庇护。",
    "体长": "54 cm",
    "体重": null,
    "寿命": "寿命较长，在自然条件下可能超过10年，具体寿命数据缺乏详细研究。",
    "适温": "25-30 °C"
  },
  "bait_options": [
    "米诺",
    "铅笔",
    "波扒",
    "软饵（卷尾蛆）",
    "软饵（小鱼型）",
    "亮片",
    "金属VIB",
    "橡胶小虾",
    "胡须佬",
    "铁板",
    "实战技巧",
    "搜索礁盘边缘和结构复杂区域，这些地方通常是斜颌猪齿鱼的藏身之处。",
    "根据水深和鱼的活性变换泳层，尝试表层、中层和底层搜索。",
    "尝试不同颜色和类型的路亚，找到当日最有效的拟饵。",
    "注意操控手法，模仿小鱼或虾的自然游动姿态，增加诱鱼效果。",
    "使用PE线和碳氟线前导线，提高鱼讯传递和耐磨性。",
    "推荐钓点类型",
    "珊瑚礁区、岩礁区、近岸水域、防波堤、码头附近",
    "相似鱼种",
    "隆头鱼",
    "鹦鹉鱼",
    "石斑鱼",
    "snapper",
    "蝴蝶鱼"
  ],
  "float_signals": [],
  "practical_tips": [
    "搜索礁盘边缘和结构复杂区域，这些地方通常是斜颌猪齿鱼的藏身之处。",
    "根据水深和鱼的活性变换泳层，尝试表层、中层和底层搜索。",
    "尝试不同颜色和类型的路亚，找到当日最有效的拟饵。",
    "注意操控手法，模仿小鱼或虾的自然游动姿态，增加诱鱼效果。",
    "使用PE线和碳氟线前导线，提高鱼讯传递和耐磨性。"
  ],
  "recommended_spots": "珊瑚礁区、岩礁区、近岸水域、防波堤、码头附近",
  "distribution": [],
  "similar_fish": [
    "隆头鱼",
    "鹦鹉鱼",
    "石斑鱼",
    "snapper",
    "蝴蝶鱼"
  ],
  "images": {
    "fish": [
      "https://fishweather.cn/asset-images/fish/shen-kou-yu.webp"
    ],
    "catch": []
  },
  "profile_text_sha256": "957a56be530d7b2e74d57d338838023c2d3d76d2044ef13ad7c24a7a53d61d6f",
  "raw_line_count": 55,
  "local_dir": "by_family/隆头鱼科/shen-kou-yu_伸口鱼",
  "local_images": {
    "fish": [
      "by_family/隆头鱼科/shen-kou-yu_伸口鱼/images/main.webp"
    ],
    "catch": []
  }
}